RequestsLibrary/RequestsKeywords.py
RequestsLibrary/__init__.py
RequestsLibrary/compat.py
RequestsLibrary/version.py
protobuf_robotframework_requests-0.1.2.dist-info/LICENSE.md
protobuf_robotframework_requests-0.1.2.dist-info/METADATA
protobuf_robotframework_requests-0.1.2.dist-info/WHEEL
protobuf_robotframework_requests-0.1.2.dist-info/top_level.txt
protobuf_robotframework_requests-0.1.2.dist-info/RECORD
